Proyecto_PCI-main/probador_1.v
module probador_1(
    input [7:0]dataOut0,
    input [7:0]dataOut1,
    input [7:0]dataOut2,
    input [7:0]dataOut3,
    input [7:0]dataOut4,
    input [7:0]dataOut5,
    input [7:0]dataOut6,
    input [7:0]dataOut7,
    input [7:0]dataOut8,
    input validOut0,
    input validOut1,
    input validOut2,
    input validOut3,
    input validOut4,
    input validOut5,
    input validOut6,
    input validOut7,
    input validOut8,
    output reg [7:0]dataIn0,
    output reg [7:0]dataIn1,
    output reg [7:0]dataIn2,
    output reg [7:0]dataIn3,
    output reg validIn0,
    output reg validIn1,
    output reg validIn2,
    output reg validIn3,
    output reg selector0,
    output reg selector1,
    output reg clk_1,
    output reg clk_2,
    output reg clk_3,
    output reg reset);

    initial begin
        $dumpfile ("Prueba_1.vcd");
        $dumpvars;

        {reset, selector0,selector1} = 1'b0;
        {validIn0, validIn1, validIn2, validIn3} = 1'b0;
        {dataIn0, dataIn1, dataIn2, dataIn3} = 8'b00000000;

        repeat (1) begin
            @(posedge clk_3);
                reset <= 0;
        end 

        @(posedge clk_1);
            selector1<=1;
        @(posedge clk_2);
            reset <= 1;
            selector1<=0;
        @(posedge clk_1);
            selector1<=1;

        @(posedge clk_3);
            dataIn0 <= 8'b11111111;
            dataIn1 <= 8'b11101110;
            dataIn2 <= 8'b11011101;
            dataIn3 <= 8'b11001100;
            validIn0 <= 1'b1;
            validIn1 <= 1'b1;
            validIn2 <= 1'b1;
            validIn3 <= 1'b1;
            selector1<=0;

        @(posedge clk_1);
            selector1<=1;
        @(posedge clk_2);
            selector0<=1;
            selector1<=0;
        @(posedge clk_1);
            selector1<=1;
		
        @(posedge clk_3);
            dataIn0 <= 8'b10111011; //BB
            dataIn1 <= 8'b10101010; //AA
            dataIn2 <= 8'b10011001; //99
            dataIn3 <= 8'b10001000; //88
            selector0<=0;
            selector1<=0;
        
        @(posedge clk_1);
            selector1<=1;
        @(posedge clk_2);
            selector0<=1;
            selector1<=0;
        @(posedge clk_1);
            selector1<=1;
            
        @(posedge clk_3);
            dataIn0 <= 8'b00000000;
            dataIn1 <= 8'b00000000;
            dataIn2 <= 8'b1110111; //77
            dataIn3 <= 8'b00000000;
            validIn0 <= 1'b0;
            validIn1 <= 1'b0;
            validIn2 <= 1'b1;
            validIn3 <= 1'b0;
            selector0<=0;
            selector1<=0;

        @(posedge clk_1);
            selector1<=1;
        @(posedge clk_2);
            selector0<=1;
            selector1<=0;
        @(posedge clk_1);
            selector1<=1;

        @(posedge clk_3);
            dataIn2 <= 8'b00000000;
            validIn2 <= 0;
            selector0<=0;
            selector1<=0;
        
        @(posedge clk_1);
            selector1<=1;
        @(posedge clk_2);
            selector0<=1;
            selector1<=0;
        @(posedge clk_1);
            selector1<=1;

        @(posedge clk_3);
            selector0<=0;
            selector1<=0;

        @(posedge clk_1);
            selector1<=1;
        @(posedge clk_2);
            selector0<=1;
            selector1<=0;
        @(posedge clk_1);
            selector1<=1;
            
        @(posedge clk_3);
            selector0<=0;
            selector1<=0;

        @(posedge clk_1);
            selector1<=1;
        @(posedge clk_2);
            selector0<=1;
            selector1<=0;
        @(posedge clk_1);
            selector1<=1;
        
        $finish;
    end

    initial	clk_1 	<= 2;
    initial	clk_2 	<= 1;
    initial clk_3   <= 1;
	always	#1 clk_1 	<= ~clk_1;
    always	#2 clk_2 	<= ~clk_2;
    always	#4 clk_3 	<= ~clk_3;
endmodule

Proyecto_PCI-main/DeMux2x1.v
module DeMux2x1(
    output reg [7:0]dataOut0,
    output reg [7:0]dataOut1,
    output reg validOut0,
    output reg validOut1,
    input [7:0]dataIn,
    input validIn,
    input selector,
    input clk,
    input reset);

    reg [7:0]out0;
    reg [7:0]out1;
    reg validDeMux0;
    reg validDeMux1;
    


    //Mux de entrada el que escoge entre dataIn1 y dataIn0 a partir del selector
    always @(*)
        begin
        out1 = 7'b0;
        out0 = 7'b0;
    	validDeMux0 = 0;
    	validDeMux1 = 0;
            if(selector == 1) begin
                out1 = dataIn;
                validDeMux1 = validIn;
            end
            else if (selector == 0)begin
                out0 = dataIn;
                validDeMux0 = validIn;
            end
        end
    // Flop que guarda lo que sea que este ee el cable out que conecta el mux con el flop
    always @(posedge clk)
        begin
            if (reset == 0)begin
                dataOut0 <= 8'b00000000;
                dataOut1 <= 8'b00000000;
            end
            else begin
                if (validDeMux0 == 1)begin
                    dataOut0 <= out0;
                    validOut0 <= validDeMux0;
                    end
                else if (validDeMux0 == 0) begin
                    dataOut0 <= dataOut0; 
                    validOut0 <= validDeMux0;   
                end
            end
        end
    always @(posedge clk) 
        begin
            if (reset == 0)begin
                    dataOut0 <= 8'b00000000;
                    dataOut1 <= 8'b00000000;
                end
            else begin
                if (validDeMux1 == 1)begin
                    dataOut1 <= out1;
                    validOut1 <= validDeMux1;
                    end
                else if (validDeMux1 == 0) begin
                    dataOut1 <= dataOut1; 
                    validOut1 <= validDeMux1;   
                end
            end
        end
endmodule

Proyecto_PCI-main/DeMuxL1.v
`include "DeMux2x1.v"
module DeMuxL1(
    output [7:0]dataOut0,
    output [7:0]dataOut1,
    output [7:0]dataOut2,
    output [7:0]dataOut3,
    output validOut0,
    output validOut1,
    output validOut2,
    output validOut3,
    input [7:0]dataIn0,
    input [7:0]dataIn1,
    input validIn0,
    input validIn1,
    input selector,
    input clk,
    input reset);

    DeMux2x1 Demux1(
        //Outputs
        .dataOut0  (dataOut0[7:0]),
        .dataOut1  (dataOut1[7:0]),  
        .validOut0 (validOut0),
        .validOut1 (validOut1),
        //Inputs
        .dataIn    (dataIn0[7:0]),
        .validIn   (validIn0),
        .selector  (selector),
        .clk       (clk),
        .reset     (reset)
    );
    
    DeMux2x1 Demux2(
        //Outputs
        .dataOut0  (dataOut2[7:0]),
        .dataOut1  (dataOut3[7:0]),  
        .validOut0 (validOut2),
        .validOut1 (validOut3),
        //Inputs
        .dataIn    (dataIn1[7:0]),
        .validIn   (validIn1),
        .selector  (selector),
        .clk       (clk),
        .reset     (reset)
    );
endmodule

Proyecto_PCI-main/DeMuxL2.v
`include "DeMux2x1.v"
module DeMuxL2(
    output [7:0]dataOut0,
    output [7:0]dataOut1,
    output validOut0,
    output validOut1,
    input [7:0]dataIn,
    input validIn,
    input selector,
    input clk,
    input reset);

    DeMux2x1 Demux(
        //Outputs
        .dataOut0  (dataOut0[7:0]),
        .dataOut1  (dataOut1[7:0]),  
        .validOut0 (validOut0),
        .validOut1 (validOut1),
        //Inputs
        .dataIn    (dataIn[7:0]),
        .validIn   (validIn),
        .selector  (selector),
        .clk       (clk),
        .reset     (reset)
    );
endmodule

Mux2x1.v
module Mux2x1(
    output reg [7:0]dataOut,
    output reg validOut,
    input [7:0]dataIn0,
    input [7:0]dataIn1,
    input validIn0,
    input validIn1,
    input selector,
    input clk,
    input reset);

    reg [7:0]out;
    reg validMux;

    //Mux de entrada el que escoge entre dataIn1 y dataIn0 a partir del selector
    always @(*)
        begin
            if(selector==0) begin
                out = dataIn0;
                validMux = validIn0;
            end
            else if (selector==1)begin
                out = dataIn1;
                validMux = validIn1;
            end
        end
    // Flop que guarda lo que sea que este ee el cable out que conecta el mux con el flop
    always @(posedge clk)
        begin
            if (reset == 0)
                dataOut <= 8'b00000000;
            else begin
                if (validMux == 1)begin
                    dataOut <= out;
                    validOut <= validMux;
                    end
                else begin
                    dataOut <= dataOut; 
                    validOut <= validMux;   
                end
            end
        end
endmodule

Proyecto_PCI-main/MuxL2.v
`include "Mux2x1.v"

module MuxL2(
    output [7:0]dataOut,
    output validOut,
    input [7:0]dataIn0,
    input [7:0]dataIn1,
    input validIn0,
    input validIn1,
    input selector,
    input clk,
    input reset);

    Mux2x1 mux1(
        //Outputs
        .dataOut  (dataOut[7:0]),
        .validOut (validOut),
        //Inputs
        .dataIn0  (dataIn0[7:0]),
        .dataIn1  (dataIn1[7:0]),
        .validIn0 (validIn0),
        .validIn1 (validIn1),
        .selector (selector),
        .clk      (clk),
        .reset    (reset)
    );
endmodule

MuxL1.v
`include "Mux2x1.v"

module MuxL1(
    output [7:0]dataOut0,
    output [7:0]dataOut1,
    output validOut0,
    output validOut1,
    input [7:0]dataIn0,
    input [7:0]dataIn1,
    input [7:0]dataIn2,
    input [7:0]dataIn3,
    input validIn0,
    input validIn1,
    input validIn2,
    input validIn3,
    input selector,
    input clk,
    input reset);

    Mux2x1 mux1(
        //Outputs
        .dataOut  (dataOut0[7:0]),
        .validOut (validOut0),
        //Inputs
        .dataIn0  (dataIn0[7:0]),
        .dataIn1  (dataIn1[7:0]),
        .validIn0 (validIn0),
        .validIn1 (validIn1),
        .selector (selector),
        .clk      (clk),
        .reset    (reset)
    );

    Mux2x1 mux2(
        //Outputs
        .dataOut  (dataOut1[7:0]),
        .validOut (validOut1),
        //Inputs
        .dataIn0  (dataIn2[7:0]),
        .dataIn1  (dataIn3[7:0]),
        .validIn0 (validIn2),
        .validIn1 (validIn3),
        .selector (selector),
        .clk      (clk),
        .reset    (reset)
    );
endmodule

Proyecto_PCI-main/BancoPrueba_1.v
`timescale 	1ns	/ 1ns

`include "MuxL1.v"
`include "MuxL2.v"
`include "DeMuxL1.v"
`include "DeMuxL2.v"
`include "probador_1.v"

module BancoPrueba_1;
	wire validIn0, validIn1, validIn2, validIn3;
	wire validOut0, validOut1, validOut2, validOut3,validOut4, validOut5, validOut6, validOut7, validOut8;
	wire [7:0] dataIn0, dataIn1, dataIn2, dataIn3;
	wire [7:0] dataOut0, dataOut1, dataOut2, dataOut3, dataOut4, dataOut5, dataOut6, dataOut7, dataOut8;
	wire clk_1, clk_2, clk_3,reset;
	wire selector0, selector1;

	MuxL1	L1( /*AUTOINST*/
				   // Outputs
				   .dataOut0		(dataOut0[7:0]),
				   .dataOut1		(dataOut1[7:0]),
				   .validOut0		(validOut0),
				   .validOut1		(validOut1),
				   // Inputs
				   .dataIn0		(dataIn0[7:0]),
				   .dataIn1		(dataIn1[7:0]),
				   .dataIn2		(dataIn2[7:0]),
				   .dataIn3		(dataIn3[7:0]),
				   .validIn0		(validIn0),
				   .validIn1		(validIn1),
				   .validIn2		(validIn2),
				   .validIn3		(validIn3),
				   .selector		(selector0),
				   .clk			(clk_2),
				   .reset		(reset));

	MuxL2 			L2( /*AUTOINST*/
				   // Outputs
				   .dataOut		(dataOut2[7:0]),
				   .validOut		(validOut2),
				   // Inputs
				   .dataIn0		(dataOut0[7:0]),
				   .dataIn1		(dataOut1[7:0]),
				   .validIn0		(validOut0),
				   .validIn1		(validOut1),
				   .selector		(selector1),
				   .clk			(clk_1),
				   .reset		(reset));
	
	DeMuxL2 		DeL2( /*AUTOINST*/
				   // Outputs
				   .dataOut0		(dataOut3[7:0]),
				   .dataOut1		(dataOut4[7:0]),
				   .validOut0		(validOut3),
				   .validOut1		(validOut4),
				   // Inputs
				   .dataIn		    (dataOut2[7:0]),
				   .validIn		    (validOut2),
				   .selector		(selector1),
				   .clk			    (clk_2),
				   .reset		    (reset));

	DeMuxL1			DeL1( /*AUTOINST*/
				   // Outputs
				   .dataOut0		(dataOut5[7:0]),
				   .dataOut1		(dataOut6[7:0]),
				   .dataOut2		(dataOut7[7:0]),
				   .dataOut3		(dataOut8[7:0]),
				   .validOut0		(validOut5),
				   .validOut1		(validOut6),
				   .validOut2		(validOut7),
				   .validOut3		(validOut8),
				   // Inputs
				   .dataIn0		(dataOut3[7:0]),
				   .dataIn1		(dataOut4[7:0]),
				   .validIn0		(validOut3),
				   .validIn1		(validOut4),
				   .selector		(selector0),
				   .clk				(clk_3),
				   .reset			(reset));

	probador_1 			probador( /*AUTOINST*/
						 // Outputs
						 .dataIn0		(dataIn0[7:0]),
						 .dataIn1		(dataIn1[7:0]),
						 .dataIn2		(dataIn2[7:0]),
						 .dataIn3		(dataIn3[7:0]),
						 .validIn0		(validIn0),
						 .validIn1		(validIn1),
						 .validIn2		(validIn2),
						 .validIn3		(validIn3),
						 .selector0		(selector0),
						 .selector1		(selector1),
						 .clk_1			(clk_1),
						 .clk_2			(clk_2),
						 .clk_3 		(clk_3),
						 .reset			(reset),
						 // Inputs
						 .dataOut0		(dataOut0[7:0]),
						 .dataOut1		(dataOut1[7:0]),
						 .dataOut2		(dataOut2[7:0]),
						 .dataOut3		(dataOut3[7:0]),
						 .dataOut4		(dataOut4[7:0]),
						 .dataOut5		(dataOut5[7:0]),
						 .dataOut6		(dataOut6[7:0]),
						 .dataOut7		(dataOut7[7:0]),
						 .dataOut8		(dataOut8[7:0]),
						 .validOut0		(validOut0),
						 .validOut1		(validOut1),
						 .validOut2		(validOut2),
						 .validOut3		(validOut3),
						 .validOut4		(validOut4),
						 .validOut5		(validOut5),
						 .validOut6		(validOut6),
						 .validOut7		(validOut7),
						 .validOut8		(validOut8)
						 );
endmodule

Proyecto_PCI-main/tmp/Prueba_1.vcd
$date
	Mon May 24 20:23:35 2021
$end
$version
	Icarus Verilog
$end
$timescale
	1ns
$end
$scope module BancoPrueba_1 $end
$var wire 1 ! validOut8 $end
$var wire 1 " validOut7 $end
$var wire 1 # validOut6 $end
$var wire 1 $ validOut5 $end
$var wire 1 % validOut4 $end
$var wire 1 & validOut3 $end
$var wire 1 ' validOut2 $end
$var wire 1 ( validOut1 $end
$var wire 1 ) validOut0 $end
$var wire 1 * validIn3 $end
$var wire 1 + validIn2 $end
$var wire 1 , validIn1 $end
$var wire 1 - validIn0 $end
$var wire 1 . selector1 $end
$var wire 1 / selector0 $end
$var wire 1 0 reset $end
$var wire 8 1 dataOut8 [7:0] $end
$var wire 8 2 dataOut7 [7:0] $end
$var wire 8 3 dataOut6 [7:0] $end
$var wire 8 4 dataOut5 [7:0] $end
$var wire 8 5 dataOut4 [7:0] $end
$var wire 8 6 dataOut3 [7:0] $end
$var wire 8 7 dataOut2 [7:0] $end
$var wire 8 8 dataOut1 [7:0] $end
$var wire 8 9 dataOut0 [7:0] $end
$var wire 8 : dataIn3 [7:0] $end
$var wire 8 ; dataIn2 [7:0] $end
$var wire 8 < dataIn1 [7:0] $end
$var wire 8 = dataIn0 [7:0] $end
$var wire 1 > clk_3 $end
$var wire 1 ? clk_2 $end
$var wire 1 @ clk_1 $end
$scope module DeL1 $end
$var wire 1 ! validOut3 $end
$var wire 1 " validOut2 $end
$var wire 1 # validOut1 $end
$var wire 1 $ validOut0 $end
$var wire 1 % validIn1 $end
$var wire 1 & validIn0 $end
$var wire 1 / selector $end
$var wire 1 0 reset $end
$var wire 8 A dataOut3 [7:0] $end
$var wire 8 B dataOut2 [7:0] $end
$var wire 8 C dataOut1 [7:0] $end
$var wire 8 D dataOut0 [7:0] $end
$var wire 8 E dataIn1 [7:0] $end
$var wire 8 F dataIn0 [7:0] $end
$var wire 1 > clk $end
$scope module Demux1 $end
$var wire 1 & validIn $end
$var wire 1 / selector $end
$var wire 1 0 reset $end
$var wire 8 G dataIn [7:0] $end
$var wire 1 > clk $end
$var reg 8 H dataOut0 [7:0] $end
$var reg 8 I dataOut1 [7:0] $end
$var reg 8 J out0 [7:0] $end
$var reg 8 K out1 [7:0] $end
$var reg 1 L validDeMux0 $end
$var reg 1 M validDeMux1 $end
$var reg 1 $ validOut0 $end
$var reg 1 # validOut1 $end
$upscope $end
$scope module Demux2 $end
$var wire 1 % validIn $end
$var wire 1 / selector $end
$var wire 1 0 reset $end
$var wire 8 N dataIn [7:0] $end
$var wire 1 > clk $end
$var reg 8 O dataOut0 [7:0] $end
$var reg 8 P dataOut1 [7:0] $end
$var reg 8 Q out0 [7:0] $end
$var reg 8 R out1 [7:0] $end
$var reg 1 S validDeMux0 $end
$var reg 1 T validDeMux1 $end
$var reg 1 " validOut0 $end
$var reg 1 ! validOut1 $end
$upscope $end
$upscope $end
$scope module DeL2 $end
$var wire 1 % validOut1 $end
$var wire 1 & validOut0 $end
$var wire 1 ' validIn $end
$var wire 1 . selector $end
$var wire 1 0 reset $end
$var wire 8 U dataOut1 [7:0] $end
$var wire 8 V dataOut0 [7:0] $end
$var wire 8 W dataIn [7:0] $end
$var wire 1 ? clk $end
$scope module Demux $end
$var wire 1 ' validIn $end
$var wire 1 . selector $end
$var wire 1 0 reset $end
$var wire 8 X dataIn [7:0] $end
$var wire 1 ? clk $end
$var reg 8 Y dataOut0 [7:0] $end
$var reg 8 Z dataOut1 [7:0] $end
$var reg 8 [ out0 [7:0] $end
$var reg 8 \ out1 [7:0] $end
$var reg 1 ] validDeMux0 $end
$var reg 1 ^ validDeMux1 $end
$var reg 1 & validOut0 $end
$var reg 1 % validOut1 $end
$upscope $end
$upscope $end
$scope module L1 $end
$var wire 1 ( validOut1 $end
$var wire 1 ) validOut0 $end
$var wire 1 * validIn3 $end
$var wire 1 + validIn2 $end
$var wire 1 , validIn1 $end
$var wire 1 - validIn0 $end
$var wire 1 / selector $end
$var wire 1 0 reset $end
$var wire 8 _ dataOut1 [7:0] $end
$var wire 8 ` dataOut0 [7:0] $end
$var wire 8 a dataIn3 [7:0] $end
$var wire 8 b dataIn2 [7:0] $end
$var wire 8 c dataIn1 [7:0] $end
$var wire 8 d dataIn0 [7:0] $end
$var wire 1 ? clk $end
$scope module mux1 $end
$var wire 1 , validIn1 $end
$var wire 1 - validIn0 $end
$var wire 1 / selector $end
$var wire 1 0 reset $end
$var wire 8 e dataIn1 [7:0] $end
$var wire 8 f dataIn0 [7:0] $end
$var wire 1 ? clk $end
$var reg 8 g dataOut [7:0] $end
$var reg 8 h out [7:0] $end
$var reg 1 i validMux $end
$var reg 1 ) validOut $end
$upscope $end
$scope module mux2 $end
$var wire 1 * validIn1 $end
$var wire 1 + validIn0 $end
$var wire 1 / selector $end
$var wire 1 0 reset $end
$var wire 8 j dataIn1 [7:0] $end
$var wire 8 k dataIn0 [7:0] $end
$var wire 1 ? clk $end
$var reg 8 l dataOut [7:0] $end
$var reg 8 m out [7:0] $end
$var reg 1 n validMux $end
$var reg 1 ( validOut $end
$upscope $end
$upscope $end
$scope module L2 $end
$var wire 8 o dataIn0 [7:0] $end
$var wire 8 p dataIn1 [7:0] $end
$var wire 1 ) validIn0 $end
$var wire 1 ( validIn1 $end
$var wire 1 ' validOut $end
$var wire 1 . selector $end
$var wire 1 0 reset $end
$var wire 8 q dataOut [7:0] $end
$var wire 1 @ clk $end
$scope module mux1 $end
$var wire 8 r dataIn0 [7:0] $end
$var wire 8 s dataIn1 [7:0] $end
$var wire 1 ) validIn0 $end
$var wire 1 ( validIn1 $end
$var wire 1 . selector $end
$var wire 1 0 reset $end
$var wire 1 @ clk $end
$var reg 8 t dataOut [7:0] $end
$var reg 8 u out [7:0] $end
$var reg 1 v validMux $end
$var reg 1 ' validOut $end
$upscope $end
$upscope $end
$scope module probador $end
$var wire 8 w dataOut0 [7:0] $end
$var wire 8 x dataOut1 [7:0] $end
$var wire 8 y dataOut2 [7:0] $end
$var wire 8 z dataOut3 [7:0] $end
$var wire 8 { dataOut4 [7:0] $end
$var wire 8 | dataOut5 [7:0] $end
$var wire 8 } dataOut6 [7:0] $end
$var wire 8 ~ dataOut7 [7:0] $end
$var wire 8 !" dataOut8 [7:0] $end
$var wire 1 ) validOut0 $end
$var wire 1 ( validOut1 $end
$var wire 1 ' validOut2 $end
$var wire 1 & validOut3 $end
$var wire 1 % validOut4 $end
$var wire 1 $ validOut5 $end
$var wire 1 # validOut6 $end
$var wire 1 " validOut7 $end
$var wire 1 ! validOut8 $end
$var reg 1 @ clk_1 $end
$var reg 1 ? clk_2 $end
$var reg 1 > clk_3 $end
$var reg 8 "" dataIn0 [7:0] $end
$var reg 8 #" dataIn1 [7:0] $end
$var reg 8 $" dataIn2 [7:0] $end
$var reg 8 %" dataIn3 [7:0] $end
$var reg 1 0 reset $end
$var reg 1 / selector0 $end
$var reg 1 . selector1 $end
$var reg 1 - validIn0 $end
$var reg 1 , validIn1 $end
$var reg 1 + validIn2 $end
$var reg 1 * validIn3 $end
$upscope $end
$upscope $end
$enddefinitions $end
#0
$dumpvars
b0 %"
b0 $"
b0 #"
b0 ""
b0 !"
b0 ~
b0 }
b0 |
b0 {
b0 z
b0 y
b0 x
b0 w
xv
b0 u
b0 t
b0 s
b0 r
b0 q
b0 p
b0 o
0n
b0 m
b0 l
b0 k
b0 j
0i
b0 h
b0 g
b0 f
b0 e
b0 d
b0 c
b0 b
b0 a
b0 `
b0 _
x^
x]
bx \
b0 [
b0 Z
b0 Y
b0 X
b0 W
b0 V
b0 U
xT
xS
bx R
b0 Q
b0 P
b0 O
b0 N
xM
xL
bx K
b0 J
b0 I
b0 H
b0 G
b0 F
b0 E
b0 D
b0 C
b0 B
b0 A
1@
1?
1>
b0 =
b0 <
b0 ;
b0 :
b0 9
b0 8
b0 7
b0 6
b0 5
b0 4
b0 3
b0 2
b0 1
00
0/
0.
0-
0,
0+
0*
x)
x(
x'
x&
x%
x$
x#
x"
x!
$end
#1
0@
#2
b0 \
1.
1@
0?
#3
0@
#4
0.
10
1@
1?
0>
#5
0@
#6
1.
1@
0?
#7
0@
#8
0v
1n
b11011101 m
1i
b11111111 h
0)
0(
0.
1*
1+
1,
1-
b11001100 :
b11001100 a
b11001100 j
b11001100 %"
b11011101 ;
b11011101 b
b11011101 k
b11011101 $"
b11101110 <
b11101110 c
b11101110 e
b11101110 #"
b11111111 =
b11111111 d
b11111111 f
b11111111 ""
1@
1?
1>
#9
0@
#10
0^
1.
0'
1@
0?
#11
0@
#12
0]
1v
b11111111 u
b0 K
0T
b0 R
b11101110 h
b11001100 m
0%
1(
b11011101 8
b11011101 _
b11011101 l
b11011101 p
b11011101 s
b11011101 x
1)
b11111111 9
b11111111 `
b11111111 g
b11111111 o
b11111111 r
b11111111 w
0.
1/
1@
1?
0>
#13
0@
#14
b11011101 u
1^
b11111111 \
1.
1'
b11111111 7
b11111111 W
b11111111 X
b11111111 q
b11111111 t
b11111111 y
1@
0?
#15
0@
#16
1]
b11011101 [
b11101110 u
0L
1S
b11111111 Q
b10011001 m
b10111011 h
b11011101 7
b11011101 W
b11011101 X
b11011101 q
b11011101 t
b11011101 y
b11101110 9
b11101110 `
b11101110 g
b11101110 o
b11101110 r
b11101110 w
b11001100 8
b11001100 _
b11001100 l
b11001100 p
b11001100 s
b11001100 x
0&
1%
b11111111 5
b11111111 E
b11111111 N
b11111111 U
b11111111 Z
b11111111 {
0!
0.
0/
b10001000 :
b10001000 a
b10001000 j
b10001000 %"
b10011001 ;
b10011001 b
b10011001 k
b10011001 $"
b10101010 <
b10101010 c
b10101010 e
b10101010 #"
b10111011 =
b10111011 d
b10111011 f
b10111011 ""
1@
1?
1>
#17
0@
#18
b11001100 u
b11101110 \
1.
b11101110 7
b11101110 W
b11101110 X
b11101110 q
b11101110 t
b11101110 y
1@
0?
#19
0@
#20
b11001100 [
b10111011 u
1M
b11011101 K
1T
b11101110 R
b10101010 h
b10001000 m
b11001100 7
b11001100 W
b11001100 X
b11001100 q
b11001100 t
b11001100 y
b11101110 5
b11101110 E
b11101110 N
b11101110 U
b11101110 Z
b11101110 {
1&
b11011101 6
b11011101 F
b11011101 G
b11011101 V
b11011101 Y
b11011101 z
b10011001 8
b10011001 _
b10011001 l
b10011001 p
b10011001 s
b10011001 x
b10111011 9
b10111011 `
b10111011 g
b10111011 o
b10111011 r
b10111011 w
0.
1/
1@
1?
0>
#21
0@
#22
b10011001 u
b10111011 \
1.
b10111011 7
b10111011 W
b10111011 X
b10111011 q
b10111011 t
b10111011 y
1@
0?
#23
0@
#24
b10011001 [
b10101010 u
1L
b11001100 J
b10111011 Q
b1110111 m
0i
b0 h
b10011001 7
b10011001 W
b10011001 X
b10011001 q
b10011001 t
b10011001 y
b10101010 9
b10101010 `
b10101010 g
b10101010 o
b10101010 r
b10101010 w
b10001000 8
b10001000 _
b10001000 l
b10001000 p
b10001000 s
b10001000 x
b11001100 6
b11001100 F
b11001100 G
b11001100 V
b11001100 Y
b11001100 z
b10111011 5
b10111011 E
b10111011 N
b10111011 U
b10111011 Z
b10111011 {
1!
b11101110 1
b11101110 A
b11101110 P
b11101110 !"
1"
b11111111 2
b11111111 B
b11111111 O
b11111111 ~
1#
b11011101 3
b11011101 C
b11011101 I
b11011101 }
0$
0.
0/
0*
0,
0-
b0 :
b0 a
b0 j
b0 %"
b1110111 ;
b1110111 b
b1110111 k
b1110111 $"
b0 <
b0 c
b0 e
b0 #"
b0 =
b0 d
b0 f
b0 ""
1@
1?
1>
#25
0@
#26
b10001000 u
b10101010 \
1.
b10101010 7
b10101010 W
b10101010 X
b10101010 q
b10101010 t
b10101010 y
1@
0?
#27
0@
#28
b10001000 [
0v
b10101010 u
b10011001 K
b10101010 R
0n
b0 m
b10001000 7
b10001000 W
b10001000 X
b10001000 q
b10001000 t
b10001000 y
b10101010 5
b10101010 E
b10101010 N
b10101010 U
b10101010 Z
b10101010 {
b10011001 6
b10011001 F
b10011001 G
b10011001 V
b10011001 Y
b10011001 z
b1110111 8
b1110111 _
b1110111 l
b1110111 p
b1110111 s
b1110111 x
0)
0.
1/
1@
1?
0>
#29
0@
#30
1v
b1110111 u
0^
b10001000 \
1.
0'
1@
0?
#31
0@
#32
b1110111 [
0v
b10101010 u
b10001000 J
0S
b10101010 Q
1'
b1110111 7
b1110111 W
b1110111 X
b1110111 q
b1110111 t
b1110111 y
0(
b10001000 6
b10001000 F
b10001000 G
b10001000 V
b10001000 Y
b10001000 z
0%
1$
b11001100 4
b11001100 D
b11001100 H
b11001100 |
b10011001 3
b10011001 C
b10011001 I
b10011001 }
b10111011 2
b10111011 B
b10111011 O
b10111011 ~
b10101010 1
b10101010 A
b10101010 P
b10101010 !"
0.
0/
0+
b0 ;
b0 b
b0 k
b0 $"
1@
1?
1>
#33
0@
#34
b1110111 u
b1110111 \
1.
0'
1@
0?
#35
0@
#36
0]
b10101010 u
b1110111 K
0T
b1110111 6
b1110111 F
b1110111 G
b1110111 V
b1110111 Y
b1110111 z
0.
1/
1@
1?
0>
#37
0@
#38
b1110111 u
1.
1@
0?
#39
0@
#40
b10101010 u
0L
b1110111 J
0&
0!
0"
b1110111 3
b1110111 C
b1110111 I
b1110111 }
b10001000 4
b10001000 D
b10001000 H
b10001000 |
0.
0/
1@
1?
1>
#41
0@
#42
b1110111 u
1.
1@
0?
#43
0@
#44
b10101010 u
0M
0.
1/
1@
1?
0>
#45
0@
#46
b1110111 u
1.
1@
0?
#47
0@
#48
b10101010 u
0$
0#
0.
0/
1@
1?
1>
#49
0@
#50
b1110111 u
1.
1@
0?
#51
0@
#52
b10101010 u
0.
1/
1@
1?
0>
#53
0@
#54
b1110111 u
1.
1@
0?
