probador_1.v
module probador_1(
    input [7:0]dataOut0,
    input [7:0]dataOut1,
    input [7:0]dataOut2,
    input validOut0,
    input validOut1,
    input validOut2,
    output reg [7:0]dataIn0,
    output reg [7:0]dataIn1,
    output reg [7:0]dataIn2,
    output reg [7:0]dataIn3,
    output reg validIn0,
    output reg validIn1,
    output reg validIn2,
    output reg validIn3,
    output reg selector,
    output reg clk_1,
    output reg clk_2,
    output reg reset);

    initial begin
        $dumpfile ("Prueba_1.vcd");
        $dumpvars;

        {reset, selector} = 1'b0;
        {validIn0, validIn1, validIn2, validIn3} = 1'b0;
        {dataIn0, dataIn1, dataIn2, dataIn3} = 8'b00000000;

        repeat (1) begin
            @(posedge clk_1);
                reset <= 1;
                selector <= 0;
        end 

        @(posedge clk_1);
            dataIn0 <= 8'b11111111;
            dataIn1 <= 8'b00010101;
            dataIn2 <= 8'b00110111;
            dataIn3 <= 8'b01010001;
            validIn0 <= 1'b1;
            validIn1 <= 1'b1;
            validIn2 <= 1'b1;
            validIn3 <= 1'b1;
		
        @(posedge clk_1);
            selector <= 1'b0;

        @(posedge clk_1);

        @(posedge clk_1);
            selector <= 1'b1;

        @(posedge clk_1);
            validIn0 <= 1'b0;
            validIn1 <= 1'b0;
            validIn2 <= 1'b0;
            validIn3 <= 1'b0;

        @(posedge clk_1);

        @(posedge clk_1);
            selector <= 1'b0;


        $finish;
    end

    initial	clk_1 	<= 0;
    initial	clk_2 	<= 0;
	always	#2 clk_1 	<= ~clk_1;
    always	#1 clk_2 	<= ~clk_2;
endmodule

Mux2x1.v
module Mux2x1(
    output reg [7:0]dataOut,
    output reg validOut,
    input [7:0]dataIn0,
    input [7:0]dataIn1,
    input validIn0,
    input validIn1,
    input selector,
    input clk,
    input reset);

    reg [7:0]out;
    reg validMux;

    //Mux de entrada el que escoge entre dataIn1 y dataIn0 a partir del selector
    always @(*)
        begin
            if(selector==0) begin
                out = dataIn0;
                validMux = validIn0;
            end
            else if (selector==1)begin
                out = dataIn1;
                validMux = validIn1;
            end
        end
    // Flop que guarda lo que sea que este ee el cable out que conecta el mux con el flop
    always @(posedge clk)
        begin
            if (reset == 0)
                dataOut <= 8'b00000000;
            else begin
                if (validMux == 1)begin
                    dataOut <= out;
                    validOut <= validMux;
                    end
                else begin
                    dataOut <= dataOut; 
                    validOut <= validMux;   
                end
            end
        end
endmodule

Proyecto_PCI-main/MuxL2.v
//`include "Mux2x1.v"

module MuxL2(
    output [7:0]dataOut,
    output validOut,
    input [7:0]dataIn0,
    input [7:0]dataIn1,
    input validIn0,
    input validIn1,
    input selector,
    input clk,
    input reset);

    Mux2x1 mux1(
        //Outputs
        .dataOut  (dataOut[7:0]),
        .validOut (validOut),
        //Inputs
        .dataIn0  (dataIn0[7:0]),
        .dataIn1  (dataIn1[7:0]),
        .validIn0 (validIn0),
        .validIn1 (validIn1),
        .selector (selector),
        .clk      (clk),
        .reset    (reset)
    );
endmodule

MuxL1.v
`include "Mux2x1.v"

module MuxL1(
    output [7:0]dataOut0,
    output [7:0]dataOut1,
    output validOut0,
    output validOut1,
    input [7:0]dataIn0,
    input [7:0]dataIn1,
    input [7:0]dataIn2,
    input [7:0]dataIn3,
    input validIn0,
    input validIn1,
    input validIn2,
    input validIn3,
    input selector,
    input clk,
    input reset);

    Mux2x1 mux1(
        //Outputs
        .dataOut  (dataOut0[7:0]),
        .validOut (validOut0),
        //Inputs
        .dataIn0  (dataIn0[7:0]),
        .dataIn1  (dataIn1[7:0]),
        .validIn0 (validIn0),
        .validIn1 (validIn1),
        .selector (selector),
        .clk      (clk),
        .reset    (reset)
    );

    Mux2x1 mux2(
        //Outputs
        .dataOut  (dataOut1[7:0]),
        .validOut (validOut1),
        //Inputs
        .dataIn0  (dataIn2[7:0]),
        .dataIn1  (dataIn3[7:0]),
        .validIn0 (validIn2),
        .validIn1 (validIn3),
        .selector (selector),
        .clk      (clk),
        .reset    (reset)
    );
endmodule

BancoPrueba_1.v
`timescale 	1ns	/ 1ns

`include "MuxL1.v"
`include "MuxL2.v"
`include "probador_1.v"

module BancoPrueba_1;
	wire validIn0, validIn1, validIn2, validIn3;
	wire validOut0, validOut1, validOut2;
	wire [7:0] dataIn0, dataIn1, dataIn2, dataIn3;
	wire [7:0] dataOut0, dataOut1, dataOut2;
	wire clk_1, clk_2, reset;
	wire selector;

	MuxL1			L1( /*AUTOINST*/
				   // Outputs
				   .dataOut0		(dataOut0[7:0]),
				   .dataOut1		(dataOut1[7:0]),
				   .validOut0		(validOut0),
				   .validOut1		(validOut1),
				   // Inputs
				   .dataIn0		(dataIn0[7:0]),
				   .dataIn1		(dataIn1[7:0]),
				   .dataIn2		(dataIn2[7:0]),
				   .dataIn3		(dataIn3[7:0]),
				   .validIn0		(validIn0),
				   .validIn1		(validIn1),
				   .validIn2		(validIn2),
				   .validIn3		(validIn3),
				   .selector		(selector),
				   .clk			(clk_1),
				   .reset		(reset));

	MuxL2 			L2( /*AUTOINST*/
				   // Outputs
				   .dataOut		(dataOut2[7:0]),
				   .validOut		(validOut2),
				   // Inputs
				   .dataIn0		(dataIn0[7:0]),
				   .dataIn1		(dataIn1[7:0]),
				   .validIn0		(validIn0),
				   .validIn1		(validIn1),
				   .selector		(selector),
				   .clk			(clk_1),
				   .reset		(reset));

	probador_1 			probador( /*AUTOINST*/
						 // Outputs
						 .dataIn0		(dataIn0[7:0]),
						 .dataIn1		(dataIn1[7:0]),
						 .dataIn2		(dataIn2[7:0]),
						 .dataIn3		(dataIn3[7:0]),
						 .validIn0		(validIn0),
						 .validIn1		(validIn1),
						 .validIn2		(validIn2),
						 .validIn3		(validIn3),
						 .selector		(selector),
						 .clk_1			(clk_1),
						 .clk_2			(clk_2),
						 .reset			(reset),
						 // Inputs
						 .dataOut0		(dataOut0[7:0]),
						 .dataOut1		(dataOut1[7:0]),
						 .dataOut2		(dataOut2[7:0]),
						 .validOut0		(validOut0),
						 .validOut1		(validOut1),
						 .validOut2		(validOut2));
endmodule

Prueba_1.vcd
$date
	Sat May 22 19:47:56 2021
$end
$version
	Icarus Verilog
$end
$timescale
	1ns
$end
$scope module BancoPrueba_1 $end
$var wire 1 ! validOut2 $end
$var wire 1 " validOut1 $end
$var wire 1 # validOut0 $end
$var wire 1 $ validIn3 $end
$var wire 1 % validIn2 $end
$var wire 1 & validIn1 $end
$var wire 1 ' validIn0 $end
$var wire 1 ( selector $end
$var wire 1 ) reset $end
$var wire 8 * dataOut2 [7:0] $end
$var wire 8 + dataOut1 [7:0] $end
$var wire 8 , dataOut0 [7:0] $end
$var wire 8 - dataIn3 [7:0] $end
$var wire 8 . dataIn2 [7:0] $end
$var wire 8 / dataIn1 [7:0] $end
$var wire 8 0 dataIn0 [7:0] $end
$var wire 1 1 clk_2 $end
$var wire 1 2 clk_1 $end
$scope module L1 $end
$var wire 1 " validOut1 $end
$var wire 1 # validOut0 $end
$var wire 1 $ validIn3 $end
$var wire 1 % validIn2 $end
$var wire 1 & validIn1 $end
$var wire 1 ' validIn0 $end
$var wire 1 ( selector $end
$var wire 1 ) reset $end
$var wire 8 3 dataOut1 [7:0] $end
$var wire 8 4 dataOut0 [7:0] $end
$var wire 8 5 dataIn3 [7:0] $end
$var wire 8 6 dataIn2 [7:0] $end
$var wire 8 7 dataIn1 [7:0] $end
$var wire 8 8 dataIn0 [7:0] $end
$var wire 1 2 clk $end
$scope module mux1 $end
$var wire 1 & validIn1 $end
$var wire 1 ' validIn0 $end
$var wire 1 ( selector $end
$var wire 1 ) reset $end
$var wire 8 9 dataIn1 [7:0] $end
$var wire 8 : dataIn0 [7:0] $end
$var wire 1 2 clk $end
$var reg 8 ; dataOut [7:0] $end
$var reg 8 < out [7:0] $end
$var reg 1 = validMux $end
$var reg 1 # validOut $end
$upscope $end
$scope module mux2 $end
$var wire 1 $ validIn1 $end
$var wire 1 % validIn0 $end
$var wire 1 ( selector $end
$var wire 1 ) reset $end
$var wire 8 > dataIn1 [7:0] $end
$var wire 8 ? dataIn0 [7:0] $end
$var wire 1 2 clk $end
$var reg 8 @ dataOut [7:0] $end
$var reg 8 A out [7:0] $end
$var reg 1 B validMux $end
$var reg 1 " validOut $end
$upscope $end
$upscope $end
$scope module L2 $end
$var wire 1 ! validOut $end
$var wire 1 & validIn1 $end
$var wire 1 ' validIn0 $end
$var wire 1 ( selector $end
$var wire 1 ) reset $end
$var wire 8 C dataOut [7:0] $end
$var wire 8 D dataIn1 [7:0] $end
$var wire 8 E dataIn0 [7:0] $end
$var wire 1 2 clk $end
$scope module mux1 $end
$var wire 1 & validIn1 $end
$var wire 1 ' validIn0 $end
$var wire 1 ( selector $end
$var wire 1 ) reset $end
$var wire 8 F dataIn1 [7:0] $end
$var wire 8 G dataIn0 [7:0] $end
$var wire 1 2 clk $end
$var reg 8 H dataOut [7:0] $end
$var reg 8 I out [7:0] $end
$var reg 1 J validMux $end
$var reg 1 ! validOut $end
$upscope $end
$upscope $end
$scope module probador $end
$var wire 8 K dataOut0 [7:0] $end
$var wire 8 L dataOut1 [7:0] $end
$var wire 8 M dataOut2 [7:0] $end
$var wire 1 # validOut0 $end
$var wire 1 " validOut1 $end
$var wire 1 ! validOut2 $end
$var reg 1 2 clk_1 $end
$var reg 1 1 clk_2 $end
$var reg 8 N dataIn0 [7:0] $end
$var reg 8 O dataIn1 [7:0] $end
$var reg 8 P dataIn2 [7:0] $end
$var reg 8 Q dataIn3 [7:0] $end
$var reg 1 ) reset $end
$var reg 1 ( selector $end
$var reg 1 ' validIn0 $end
$var reg 1 & validIn1 $end
$var reg 1 % validIn2 $end
$var reg 1 $ validIn3 $end
$upscope $end
$upscope $end
$enddefinitions $end
#0
$dumpvars
b0 Q
b0 P
b0 O
b0 N
bx M
bx L
bx K
0J
b0 I
bx H
b0 G
b0 F
b0 E
b0 D
bx C
0B
b0 A
bx @
b0 ?
b0 >
0=
b0 <
bx ;
b0 :
b0 9
b0 8
b0 7
b0 6
b0 5
bx 4
bx 3
02
01
b0 0
b0 /
b0 .
b0 -
bx ,
bx +
bx *
0)
0(
0'
0&
0%
0$
x#
x"
x!
$end
#1
11
#2
b0 ,
b0 4
b0 ;
b0 K
b0 +
b0 3
b0 @
b0 L
b0 *
b0 C
b0 H
b0 M
1)
01
12
#3
11
#4
01
02
#5
11
#6
1B
b110111 A
1=
b11111111 <
1J
b11111111 I
1$
1%
1&
1'
b1010001 -
b1010001 5
b1010001 >
b1010001 Q
b110111 .
b110111 6
b110111 ?
b110111 P
b10101 /
b10101 7
b10101 9
b10101 D
b10101 F
b10101 O
b11111111 0
b11111111 8
b11111111 :
b11111111 E
b11111111 G
b11111111 N
0!
0"
0#
01
12
#7
11
#8
01
02
#9
11
#10
1#
b11111111 ,
b11111111 4
b11111111 ;
b11111111 K
1"
b110111 +
b110111 3
b110111 @
b110111 L
1!
b11111111 *
b11111111 C
b11111111 H
b11111111 M
01
12
#11
11
#12
01
02
#13
11
#14
01
12
#15
11
#16
01
02
#17
11
#18
b10101 I
b10101 <
b1010001 A
1(
01
12
#19
11
#20
01
02
#21
11
#22
0B
0=
0J
0$
0%
0&
0'
b10101 *
b10101 C
b10101 H
b10101 M
b1010001 +
b1010001 3
b1010001 @
b1010001 L
b10101 ,
b10101 4
b10101 ;
b10101 K
01
12
#23
11
#24
01
02
#25
11
#26
0#
0"
0!
01
12
#27
11
#28
01
02
#29
11
#30
b11111111 I
b11111111 <
b110111 A
0(
01
12
